expectation/__init__.py
expectation_version/__init__.py
tests/__init__.py
tests/test_dummy.py
expectation-0.0.2.dist-info/LICENSE
expectation-0.0.2.dist-info/METADATA
expectation-0.0.2.dist-info/WHEEL
expectation-0.0.2.dist-info/top_level.txt
expectation-0.0.2.dist-info/RECORD
