Metadata-Version: 2.1
Name: expectation
Version: 0.0.2
Summary: Fugue data validation framework
Home-page: http://github.com/goodwanghan/expectation
Author: Han Wang
Author-email: goodwanghan@gmail.com
License: Apache-2.0
Keywords: validation expect expectation
Platform: UNKNOWN
Classifier: Development Status :: 3 - Alpha
Classifier: Intended Audience :: Developers
Classifier: Topic :: Software Development :: Libraries :: Python Modules
Classifier: License :: OSI Approved :: Apache Software License
Classifier: Programming Language :: Python :: 3.6
Classifier: Programming Language :: Python :: 3.7
Classifier: Programming Language :: Python :: 3.8
Classifier: Programming Language :: Python :: 3 :: Only
Requires-Python: >=3.6
Requires-Dist: pandas
